{
  "db_name": "SQLite",
  "query": "\n                INSERT INTO project_ref_retention_rules (\n                    id,\n                    project_id,\n                    priority,\n                    ref_pattern,\n                    ttl_seconds,\n                    keep_builds\n                )\n                VALUES (?, ?, ?, ?, ?, ?)\n                ",
  "describe": {
    "columns": [],
    "parameters": {
      "Right": 6
    },
    "nullable": []
  },
  "hash": "45d3d68abb2fc36984460263635007b98f538abbbe2c6d6e881adc926989a3fa"
}
